{
  "1": {
    "nom": "Riesling",
    "img": "img/riesling.jpg",
    "price": "5,85 €",
    "color": "white",
    "aperitif": "no",
    "maintenant": "yes",
    "cave": "no"
  },
  "2": {
    "nom": "Lillet",
    "img": "img/lillet.jpg",
    "price": "12,99 €",
    "color": "white",
    "aperitif": "yes",
    "maintenant": "yes",
    "cave": "no"
  },
  "3": {
    "nom": "Saint-Joseph",
    "img": "img/st-joseph.jpg",
    "price": "15,99 €",
    "maintenant": "no",
    "color": "white",
    "aperitif": "no",
    "cave": "yes"
  },
  "4": {
    "nom": "Domaine du Moulin de Dusenbach",
    "img": "img/dusenbach.jpg",
    "price": "9,00 €",
    "color": "red",
    "maintenant": "yes",
    "aperitif": "yes",
    "cave": "no"
  },
  "5": {
    "nom": "Château Rioublanc",
    "img": "img/rioublanc.jpg",
    "price": "66,00 €",
    "color": "red",
    "maintenant": "no",
    "aperitif": "no",
    "cave": "yes"
  },
  "6": {
    "nom": "Chateau d'Yquem 2005",
    "img": "img/yquem.jpg",
    "price": "329,00 €",
    "color": "white",
    "maintenant": "yes",
    "aperitif": "yes",
    "cave": "yes"
  },
  "7": {
    "nom": "Chardonnay",
    "img": "img/chardonnay.jpg",
    "price": "9,85€",
    "maintenant": "yes",
    "color": "white",
    "aperitif": "no",
    "cave": "no"
  },
  "8": {
    "nom": "Intuition 2013",
    "img": "img/intuition.jpg",
    "price": "23,00 €",
    "color": "red",
    "maintenant": "no",
    "aperitif": "no",
    "cave": "no"
  },
  "9": {
    "nom": "Bandol",
    "img": "img/bandol.jpg",
    "price": "23,80 €",
    "color": "rose",
    "maintenant": "yes",
    "aperitif": "no",
    "cave": "no"
  },
  "10": {
    "nom": "Coroa d'Ouro Tinto 2013",
    "img": "img/coroa.jpg",
    "price": "9,90 €",
    "maintenant": "yes",
    "color": "red",
    "aperitif": "no",
    "cave": "no"
  },
  "11": {
    "nom": "Crémant d'Alsace",
    "img": "img/cremant.jpg",
    "price": "12,90 €",
    "maintenant": "yes",
    "color": "white",
    "aperitif": "yes",
    "cave": "no"
  },
  "12": {
    "nom": "Gigondas",
    "img": "img/gigondas.jpg",
    "price": "19,90 €",
    "maintenant": "yes",
    "color": "red",
    "aperitif": "no",
    "cave": "yes"
  },
  "13": {
    "nom": "Nuits St Georges",
    "img": "img/nuits.jpg",
    "price": "149,90 €",
    "maintenant": "yes",
    "color": "red",
    "aperitif": "no",
    "cave": "yes"
  },
  "14": {
    "nom": "Michel de Montaigne",
    "img": "img/montaigne.jpg",
    "price": "49,90 €",
    "maintenant": "yes",
    "color": "white",
    "aperitif": "yes",
    "cave": "yes"
  },
  "15": {
    "nom": "Rosé des dunes",
    "img": "img/dunes.jpg",
    "price": "4,90 €",
    "maintenant": "yes",
    "color": "rose",
    "aperitif": "yes",
    "cave": "no"
  }
}